rfi/__init__.py
rfi/app.py
rfi/initiative.py
roll_for_initiative-0.16.1.dist-info/entry_points.txt
roll_for_initiative-0.16.1.dist-info/LICENSE
roll_for_initiative-0.16.1.dist-info/WHEEL
roll_for_initiative-0.16.1.dist-info/METADATA
roll_for_initiative-0.16.1.dist-info/RECORD
