Metadata-Version: 2.1
Name: roll-for-initiative
Version: 0.16.1
Summary: A CLI initiative tracker in the works.
Home-page: https://github.com/wqferr/rfi
License: UNKNOWN
Keywords: rpg initiative d&d tracker turn
Author: William Quelho Ferreira
Author-email: wqferr@gmail.com
Classifier: License :: OSI Approved :: MIT License
Classifier: Development Status :: 2 - Pre-Alpha
Classifier: Environment :: Console
Classifier: Topic :: Games/Entertainment :: Role-Playing
Classifier: Topic :: Games/Entertainment :: Turn Based Strategy
Requires-Dist: prompt-toolkit
Requires-Dist: flit
Requires-Dist: texttable
Requires-Dist: dice
